minitraceback/__init__.py
minitraceback-0.1.2.dist-info/METADATA
minitraceback-0.1.2.dist-info/WHEEL
minitraceback-0.1.2.dist-info/licenses/LICENSE.txt
minitraceback-0.1.2.dist-info/RECORD
